build_qt/__init__.py
build_qt/cli.py
build_qt/config.py
build_qt/ohos_sdk_downloader.py
build_qt/qt_build.py
build_qt/qt_repo.py
build_qt/utils.py
build_qt/ziptools/__init__.py
build_qt/ziptools/zipcruft.py
build_qt/ziptools/ziplongpaths.py
build_qt/ziptools/zipmodtimeutc.py
build_qt/ziptools/zipsymlinks.py
build_qt/ziptools/ziptools.py
build_qt-1.0.0.dist-info/licenses/LICENSE
build_qt-1.0.0.dist-info/METADATA
build_qt-1.0.0.dist-info/WHEEL
build_qt-1.0.0.dist-info/entry_points.txt
build_qt-1.0.0.dist-info/top_level.txt
build_qt-1.0.0.dist-info/RECORD
