Metadata-Version: 2.4
Name: build-qt
Version: 1.0.0
Summary: 一个用于在 Windows/Linux/macOS 上自动化构建 Qt for OpenHarmony（OHOS）的工具集
Author-email: liys-online <your.email@example.com>
License-Expression: GPL-3.0-or-later
Project-URL: Homepage, https://github.com/liys-online/build-qt
Project-URL: Repository, https://github.com/liys-online/build-qt
Project-URL: Bug Tracker, https://github.com/liys-online/build-qt/issues
Keywords: qt,openharmony,ohos,build,cross-compile
Classifier: Development Status :: 4 - Beta
Classifier: Intended Audience :: Developers
Classifier: Topic :: Software Development :: Build Tools
Classifier: Programming Language :: Python :: 3
Classifier: Programming Language :: Python :: 3.8
Classifier: Programming Language :: Python :: 3.9
Classifier: Programming Language :: Python :: 3.10
Classifier: Programming Language :: Python :: 3.11
Classifier: Programming Language :: Python :: 3.12
Classifier: Operating System :: OS Independent
Requires-Python: >=3.8
License-File: LICENSE
Requires-Dist: requests
Requires-Dist: questionary
Requires-Dist: rich
Requires-Dist: py7zr
Dynamic: license-file
